pine_ta/__init__.py
pine_ta-0.1.0.dist-info/licenses/LICENSE
pine_ta-0.1.0.dist-info/METADATA
pine_ta-0.1.0.dist-info/WHEEL
pine_ta-0.1.0.dist-info/top_level.txt
pine_ta-0.1.0.dist-info/RECORD
