Metadata-Version: 2.4
Name: pine_ta
Version: 0.1.0
Summary: Pure pandas/numpy technical indicators inspired by Pine Script
Home-page: https://github.com/huzaifazahoor/pine_ta
Author: Huzaifa Zahoor
Author-email: huzaifazahoor654@email.com
Classifier: Programming Language :: Python :: 3
Classifier: License :: OSI Approved :: MIT License
Classifier: Operating System :: OS Independent
Requires-Python: >=3.7
License-File: LICENSE
Requires-Dist: pandas
Requires-Dist: numpy
Dynamic: author
Dynamic: author-email
Dynamic: classifier
Dynamic: description
Dynamic: description-content-type
Dynamic: home-page
Dynamic: license-file
Dynamic: requires-dist
Dynamic: requires-python
Dynamic: summary
